{
    "id": "ec551ccd29d246888f35cb4a5371b7d5",
    "name": "IdentityNow Helpdesk Admin",
    "description": null,
    "created": "2023-02-09T20:56:20.087Z",
    "modified": "2023-02-09T20:56:32.485Z",
    "enabled": true,
    "owner": {
        "type": "IDENTITY",
        "id": "2c9180866b96030c016bb3440f680f1c",
        "name": "Alex Alvarez"
    },
    "source": {
        "id": "1381344b7bb34c7a89092de2e0da3eb5",
        "type": "SOURCE",
        "name": "IdentityNow Admin Roles"
    },
    "entitlements": [
        {
            "id": "77c35e1ebdcc47558587563fe1e597fc",
            "type": "ENTITLEMENT",
            "name": "Helpdesk"
        }
    ],
    "requestable": true,
    "accessRequestConfig": {
        "commentsRequired": false,
        "denialCommentsRequired": false,
        "approvalSchemes": []
    },
    "revocationRequestConfig": {
        "approvalSchemes": []
    },
    "segments": [],
    "provisioningCriteria": null,
    "segmentRefs": []
}